starlingbank/__init__.py
starlingbank-3.2.dist-info/LICENSE
starlingbank-3.2.dist-info/METADATA
starlingbank-3.2.dist-info/WHEEL
starlingbank-3.2.dist-info/top_level.txt
starlingbank-3.2.dist-info/RECORD
